setup.py
distributions_tws/Binomialdistribution.py
distributions_tws/Gaussiandistribution.py
distributions_tws/Generaldistribution.py
distributions_tws/__init__.py
distributions_tws.egg-info/PKG-INFO
distributions_tws.egg-info/SOURCES.txt
distributions_tws.egg-info/dependency_links.txt
distributions_tws.egg-info/not-zip-safe
distributions_tws.egg-info/top_level.txt